kfm/__init__.py
kfm/__main__.py
kfm/well_mapper.py
kfm-1.0.4.dist-info/LICENSE
kfm-1.0.4.dist-info/METADATA
kfm-1.0.4.dist-info/WHEEL
kfm-1.0.4.dist-info/entry_points.txt
kfm-1.0.4.dist-info/top_level.txt
kfm-1.0.4.dist-info/zip-safe
kfm-1.0.4.dist-info/RECORD
