Metadata-Version: 2.1
Name: kfm
Version: 1.0.4
Summary: A better way to manage Keyence-generated microscopy data
Home-page: https://github.com/GallowayLabMIT/kfm
Author: Nathan B. Wang
Author-email: nbwang22@gmail.com
License: MIT
Project-URL: Bug Tracker, https://github.com/GallowayLabMIT/kfm/issues
Platform: UNKNOWN
Classifier: Programming Language :: Python :: 3
Classifier: License :: OSI Approved :: MIT License
Classifier: Operating System :: OS Independent
Requires-Python: >=3.6
License-File: LICENSE
Requires-Dist: pyyaml
